toy_package/__init__.py
toy_package/math.py
toy_package/utils.py
toy_python_package_raghavajoijode-1.0.1.dist-info/LICENSE
toy_python_package_raghavajoijode-1.0.1.dist-info/METADATA
toy_python_package_raghavajoijode-1.0.1.dist-info/WHEEL
toy_python_package_raghavajoijode-1.0.1.dist-info/top_level.txt
toy_python_package_raghavajoijode-1.0.1.dist-info/RECORD
