Metadata-Version: 2.1
Name: toy-python-package-raghavajoijode
Version: 1.0.1
Summary: A toy python package
Home-page: https://github.com/raghavajoijode/toy-python-package
Author: Raghava Joijode
Author-email: raghava.joijode@gmail.com
License: UNKNOWN
Platform: UNKNOWN
Classifier: Programming Language :: Python :: 3
Classifier: License :: OSI Approved :: MIT License
Classifier: Operating System :: OS Independent
Requires-Python: >=3.6
